{"dependencies":[{"name":"history/createBrowserHistory"},{"name":"history/createMemoryHistory"},{"name":"process"}],"generated":{"js":"var process = require(\"process\");\n\"use strict\";\n\nObject.defineProperty(exports, \"__esModule\", {\n  value: true\n});\n\nvar _createBrowserHistory = require(\"history/createBrowserHistory\");\n\nvar _createBrowserHistory2 = _interopRequireDefault(_createBrowserHistory);\n\nvar _createMemoryHistory = require(\"history/createMemoryHistory\");\n\nvar _createMemoryHistory2 = _interopRequireDefault(_createMemoryHistory);\n\nfunction _interopRequireDefault(obj) { return obj && obj.__esModule ? obj : { default: obj }; }\n\nvar history = process.NODE_ENV === 'test' ? (0, _createMemoryHistory2.default)() : (0, _createBrowserHistory2.default)();\n\nexports.default = history;"},"hash":"c3d4aaa5777d7cab1dd07115e9c0995b"}